{
  "streams": [
    {
      "tap_stream_id": "testdb-test_customers",
      "table_name": "test_customers",
      "replication_method": "",
      "key_properties": [
        "replication_key"
      ],
      "schema": {
        "properties": {
          "cluster_time": {
            "format": "date-time",
            "type": [
              "string",
              "null"
            ]
          },
          "document": {
            "type": [
              "string",
              "null"
            ]
          },
          "namespace__database": {
            "type": [
              "string",
              "null"
            ]
          },
          "namespace__collection": {
            "type": [
              "string",
              "null"
            ]
          },
          "object_id": {
            "type": [
              "string",
              "null"
            ]
          },
          "operation_type": {
            "type": [
              "string",
              "null"
            ]
          },
          "replication_key": {
            "type": [
              "string"
            ]
          }
        },
        "type": "object",
        "required": [
          "replication_key"
        ],
        "$schema": "https://json-schema.org/draft/2020-12/schema"
      },
      "is_view": false,
      "stream": "testdb-test_customers",
      "metadata": [
        {
          "breadcrumb": [
            "properties",
            "cluster_time"
          ],
          "metadata": {
            "inclusion": "available",
            "selected": true
          }
        },
        {
          "breadcrumb": [
            "properties",
            "document"
          ],
          "metadata": {
            "inclusion": "available",
            "selected": true
          }
        },
        {
          "breadcrumb": [
            "properties",
            "namespace__database"
          ],
          "metadata": {
            "inclusion": "available",
            "selected": true
          }
        },
        {
          "breadcrumb": [
            "properties",
            "namespace__collection"
          ],
          "metadata": {
            "inclusion": "available",
            "selected": true
          }
        },
        {
          "breadcrumb": [
            "properties",
            "object_id"
          ],
          "metadata": {
            "inclusion": "available",
            "selected": true
          }
        },
        {
          "breadcrumb": [
            "properties",
            "operation_type"
          ],
          "metadata": {
            "inclusion": "available",
            "selected": true
          }
        },
        {
          "breadcrumb": [
            "properties",
            "replication_key"
          ],
          "metadata": {
            "inclusion": "automatic",
            "selected": true
          }
        },
        {
          "breadcrumb": [],
          "metadata": {
            "inclusion": "available",
            "table-key-properties": [
              "replication_key"
            ],
            "forced-replication-method": "",
            "schema-name": "testdb",
            "selected": false
          }
        }
      ],
      "selected": false
    },
    {
      "tap_stream_id": "testdb-test_products",
      "table_name": "test_products",
      "replication_method": "",
      "key_properties": [
        "id"
      ],
      "schema": {
        "properties": {
          "id": {
            "type": [
              "integer"
            ]
          },
          "name": {
            "type": [
              "string",
              "null"
            ]
          },
          "sku": {
            "type": [
              "string",
              "null"
            ]
          },
          "price": {
            "type": [
              "number",
              "null"
            ]
          },
          "stock": {
            "type": [
              "integer",
              "null"
            ]
          }
        },
        "type": "object",
        "required": [
          "id"
        ],
        "$schema": "https://json-schema.org/draft/2020-12/schema"
      },
      "is_view": false,
      "stream": "testdb-test_products",
      "metadata": [
        {
          "breadcrumb": [
            "properties",
            "id"
          ],
          "metadata": {
            "inclusion": "automatic",
            "selected": true
          }
        },
        {
          "breadcrumb": [
            "properties",
            "name"
          ],
          "metadata": {
            "inclusion": "available",
            "selected": true
          }
        },
        {
          "breadcrumb": [
            "properties",
            "sku"
          ],
          "metadata": {
            "inclusion": "available",
            "selected": true
          }
        },
        {
          "breadcrumb": [
            "properties",
            "price"
          ],
          "metadata": {
            "inclusion": "available",
            "selected": true
          }
        },
        {
          "breadcrumb": [
            "properties",
            "stock"
          ],
          "metadata": {
            "inclusion": "available",
            "selected": true
          }
        },
        {
          "breadcrumb": [],
          "metadata": {
            "inclusion": "available",
            "table-key-properties": [
              "id"
            ],
            "forced-replication-method": "",
            "schema-name": "testdb",
            "selected": false
          }
        }
      ],
      "selected": false
    }
  ]
}